ellipsect/__init__.py
ellipsect/ellipsectors.py
ellipsect/inout/__init__.py
ellipsect/inout/galfit.py
ellipsect/inout/gfits.py
ellipsect/inout/plots.py
ellipsect/inout/prt.py
ellipsect/inout/read.py
ellipsect/lib/__init__.py
ellipsect/lib/clas.py
ellipsect/lib/libs.py
ellipsect/phot/__init__.py
ellipsect/phot/ned.py
ellipsect/phot/phot.py
ellipsect/phot/tidal.py
ellipsect/sectors/__init__.py
ellipsect/sectors/comp.py
ellipsect/sectors/ellip.py
ellipsect/sectors/num.py
ellipsect/sectors/sect.py
ellipsect/sky/__init__.py
ellipsect/sky/sky.py
EllipSect-3.4.4.dist-info/LICENSE.txt
EllipSect-3.4.4.dist-info/METADATA
EllipSect-3.4.4.dist-info/WHEEL
EllipSect-3.4.4.dist-info/entry_points.txt
EllipSect-3.4.4.dist-info/top_level.txt
EllipSect-3.4.4.dist-info/RECORD
