Metadata-Version: 2.1
Name: EllipSect
Version: 3.4.4
Summary: A surface brightness analysis tool for GALFIT output.
Home-page: https://github.com/canorve/EllipSect
Author: Christopher Añorve
Author-email: canorve@gmail.com
License: GNU General Public License v3 (GPLv3)
Project-URL: Documentation, https://github.com/canorve/EllipSect/blob/master/README.rst
Project-URL: Source, https://github.com/canorve/EllipSect
Platform: Linux
Platform: Mac
Classifier: Programming Language :: Python
Classifier: Development Status :: 5 - Production/Stable
Classifier: Framework :: Pytest
Classifier: Intended Audience :: Science/Research
Classifier: License :: OSI Approved :: GNU General Public License v3 (GPLv3)
Classifier: Natural Language :: Spanish
Classifier: Natural Language :: English
Classifier: Topic :: Scientific/Engineering :: Astronomy
License-File: LICENSE.txt
Requires-Dist: importlib-metadata; python_version < "3.8"
Requires-Dist: importlib-metadata
Requires-Dist: sphinx>=3.2.1
Requires-Dist: numpy>=1.20.3
Requires-Dist: astropy>=5.1
Requires-Dist: scipy>=1.5.2
Requires-Dist: matplotlib>=3.5.2
Requires-Dist: mgefit>=5.0.13
Provides-Extra: testing
Requires-Dist: setuptools; extra == "testing"
Requires-Dist: pytest; extra == "testing"
Requires-Dist: pytest-cov; extra == "testing"
